[
  {
    "title": "USA",
    "drawable": "",
    "submenu": "",
    "tabs": [
      {
        "title": "Flirt Deutschland",
        "provider": "webview",
        "arguments": [
          "https://www.awin1.com/cread.php?awinmid=18366&awinaffid=625033&clickref=deutschland",
          "deals"
        ]
      },
      {
        "title": "Singles in der nähe",
        "provider": "webview",
        "arguments": [
          "https://instaquiz.app/tracking/partnersuche-dating-deutschland-cdate.html",
          "usa_new"
        ]
      },
      {
        "title": "Flirt Community",
        "provider": "webview",
        "arguments": [
          "https://socialdate.me/cpa?tds_campaign=s7107yev&tdsId=s7107yev_r&utm_source=intc&utm_campaign=df99c67c&utm_content={utm_content}&data2={data2}&utm_sub=opnfnl&s1=ps&utm_term=1",
          "usa_new"
        ]
      }
    ],
    "iap": false
  },
  {
    "title": "Other Countries",
    "drawable": "",
    "submenu": "",
    "tabs": [
      {
        "title": "Top Films and series",
        "image": "",
        "provider": "wordpress",
        "arguments": [
          "",
          "deals"
        ]
      }
    ],
    "iap": false
  },
  {
    "title": "Settings",
    "drawable": "",
    "submenu": "Other",
    "tabs": [
      {
        "title": "",
        "provider": "custom",
        "arguments": [
          "",
          "fragment"
        ]
      }
    ],
    "iap": false
  }
]
